receipt_generator/__init__.py
receipt_generator/cli.py
receipt_generator/generator.py
receipt_generator-0.1.3.dist-info/METADATA
receipt_generator-0.1.3.dist-info/WHEEL
receipt_generator-0.1.3.dist-info/entry_points.txt
receipt_generator-0.1.3.dist-info/top_level.txt
receipt_generator-0.1.3.dist-info/RECORD
