Metadata-Version: 2.1
Name: receipt_generator
Version: 0.1.3
Summary: Пакет для автоматической генерации чеков на основе заказов
Author: Nikita
